ibm_secrets_manager_sdk/__init__.py
ibm_secrets_manager_sdk/common.py
ibm_secrets_manager_sdk/secrets_manager_v2.py
ibm_secrets_manager_sdk/version.py
ibm_secrets_manager_sdk-2.1.13.dist-info/licenses/LICENSE
ibm_secrets_manager_sdk-2.1.13.dist-info/METADATA
ibm_secrets_manager_sdk-2.1.13.dist-info/WHEEL
ibm_secrets_manager_sdk-2.1.13.dist-info/top_level.txt
ibm_secrets_manager_sdk-2.1.13.dist-info/zip-safe
ibm_secrets_manager_sdk-2.1.13.dist-info/RECORD
