Metadata-Version: 2.4
Name: ibm-secrets-manager-sdk
Version: 2.1.13
Summary: IBM Cloud Secrets Manager Python SDK
Home-page: https://github.com/IBM/secrets-manager-python-sdk
Author: IBM
License: Apache 2.0
Keywords: ibm_secrets_manager_sdk
Classifier: Programming Language :: Python
Classifier: Programming Language :: Python :: 3
Classifier: Programming Language :: Python :: 3.5
Classifier: Programming Language :: Python :: 3.6
Classifier: Programming Language :: Python :: 3.7
Classifier: Programming Language :: Python :: 3.8
Classifier: Development Status :: 5 - Production/Stable
Classifier: Intended Audience :: Developers
Classifier: License :: OSI Approved :: Apache Software License
Classifier: Operating System :: OS Independent
Classifier: Topic :: Software Development :: Libraries :: Python Modules
Classifier: Topic :: Software Development :: Libraries :: Application Frameworks
License-File: LICENSE
Requires-Dist: requests<3.0.0,>=2.32.4
Requires-Dist: urllib3<3.0.0,>=2.5.0
Requires-Dist: python_dateutil<3.0.0,>=2.5.3
Requires-Dist: ibm_cloud_sdk_core<4.0.0,>=3.21.0
Dynamic: author
Dynamic: classifier
Dynamic: description
Dynamic: description-content-type
Dynamic: home-page
Dynamic: keywords
Dynamic: license
Dynamic: license-file
Dynamic: requires-dist
Dynamic: summary
